[
  {
    "pdg_node": {
      "predicate_id": "wrapperpredictionsignalcomputation",
      "statement": "(prediction: numpy.ndarray, raw_signal: numpy.ndarray) -> numpy.ndarray",
      "informal_desc": "Post-process Kazemi model scores and the aligned raw PPG segment into retained peak indices.",
      "prover": "python",
      "context": {
        "source": "/Users/conrad/personal/ageo-atoms/third_party/E2E-PPG/kazemi_peak_detection.py:69"
      }
    },
    "verified_match": {
      "candidate": {
        "declaration": {
          "name": "wrapperpredictionsignalcomputation",
          "type_signature": "(prediction: numpy.ndarray, raw_signal: numpy.ndarray) -> numpy.ndarray",
          "docstring": "Extract Kazemi wrapper peak indices from model predictions and a raw PPG segment.",
          "conceptual_summary": "Deterministic peak post-processing for an aligned PPG prediction trace.",
          "source_lib": "manual_reingest",
          "prover": "python",
          "raw_code": ""
        },
        "score": 1.0,
        "retrieval_method": "manual_reingest"
      },
      "verified": true,
      "compiler_output": "",
      "proof_term": "",
      "error_message": "",
      "verification_level": "behavior_tested"
    },
    "all_candidates": [],
    "all_verifications": []
  },
  {
    "pdg_node": {
      "predicate_id": "signalarraynormalization",
      "statement": "(arr: numpy.ndarray) -> numpy.ndarray",
      "informal_desc": "Normalize an array using the vendored Kazemi helper.",
      "prover": "python",
      "context": {
        "source": "/Users/conrad/personal/ageo-atoms/third_party/E2E-PPG/kazemi_peak_detection.py:14"
      }
    },
    "verified_match": {
      "candidate": {
        "declaration": {
          "name": "signalarraynormalization",
          "type_signature": "(arr: numpy.ndarray) -> numpy.ndarray",
          "docstring": "Normalize an input numeric array to a standard scale.",
          "conceptual_summary": "Deterministic numeric array normalization.",
          "source_lib": "manual_reingest",
          "prover": "python",
          "raw_code": ""
        },
        "score": 1.0,
        "retrieval_method": "manual_reingest"
      },
      "verified": true,
      "compiler_output": "",
      "proof_term": "",
      "error_message": "",
      "verification_level": "delegation_tested"
    },
    "all_candidates": [],
    "all_verifications": []
  }
]
